.VERSION
AUTHORS.rst
CONTRIBUTING.rst
HISTORY.rst
LICENSE
MANIFEST.in
Pipfile
Pipfile.lock
README.rst
USAGE.rst
dev-requirements.txt
requirements.txt
setup.cfg
setup.py
docs/Makefile
docs/authors.rst
docs/conf.py
docs/contributing.rst
docs/history.rst
docs/index.rst
docs/installation.rst
docs/readme.rst
docs/usage.rst
securityhubsuppressorlib/.VERSION
securityhubsuppressorlib/AUTHORS.rst
securityhubsuppressorlib/CONTRIBUTING.rst
securityhubsuppressorlib/HISTORY.rst
securityhubsuppressorlib/LICENSE
securityhubsuppressorlib/Pipfile
securityhubsuppressorlib/Pipfile.lock
securityhubsuppressorlib/README.rst
securityhubsuppressorlib/USAGE.rst
securityhubsuppressorlib/__init__.py
securityhubsuppressorlib/_version.py
securityhubsuppressorlib/dev-requirements.txt
securityhubsuppressorlib/requirements.txt
securityhubsuppressorlib/securityhubsuppressorlib.py
securityhubsuppressorlib/securityhubsuppressorlibexceptions.py
securityhubsuppressorlib.egg-info/PKG-INFO
securityhubsuppressorlib.egg-info/SOURCES.txt
securityhubsuppressorlib.egg-info/dependency_links.txt
securityhubsuppressorlib.egg-info/not-zip-safe
securityhubsuppressorlib.egg-info/top_level.txt
securityhubsuppressorlib/__pycache__/__init__.cpython-37.pyc
securityhubsuppressorlib/__pycache__/_version.cpython-37.pyc