Metadata-Version: 2.1
Name: securityhubsuppressorlib
Version: 0.0.0
Summary: Suppresses Security Hub findings based on configuration placed in DynamoDB.
Home-page: https://github.com/schubergphilis/securityhubsuppressorlib.git
Author: Costas Tyfoxylos
Author-email: ctyfoxylos@schuberpghilis.com
License: MIT
Keywords: securityhubsuppressorlib Security Hub finding suppression
Platform: UNKNOWN
Classifier: Development Status :: 4 - Beta
Classifier: Intended Audience :: Developers
Classifier: License :: OSI Approved :: MIT License
Classifier: Natural Language :: English
Classifier: Programming Language :: Python :: 3.7
License-File: LICENSE
License-File: AUTHORS.rst
